[{"party":"AfD","hashtags":"afd","weeksTillElection":-3,"freq":163},{"party":"AfD","hashtags":"afd","weeksTillElection":-2,"freq":205},{"party":"AfD","hashtags":"afd","weeksTillElection":-1,"freq":226},{"party":"AfD","hashtags":"afd","weeksTillElection":0,"freq":1219},{"party":"AfD","hashtags":"afd","weeksTillElection":1,"freq":496},{"party":"AfD","hashtags":"afd","weeksTillElection":2,"freq":455},{"party":"AfD","hashtags":"afd","weeksTillElection":3,"freq":254},{"party":"AfD","hashtags":"afd","weeksTillElection":4,"freq":263},{"party":"AfD","hashtags":"afd","weeksTillElection":5,"freq":351},{"party":"AfD","hashtags":"afd","weeksTillElection":6,"freq":206},{"party":"AfD","hashtags":"agh","weeksTillElection":-3,"freq":18},{"party":"AfD","hashtags":"barcelona","weeksTillElection":5,"freq":40},{"party":"AfD","hashtags":"btw17","weeksTillElection":0,"freq":384},{"party":"AfD","hashtags":"btw17","weeksTillElection":1,"freq":122},{"party":"AfD","hashtags":"btw17","weeksTillElection":2,"freq":133},{"party":"AfD","hashtags":"btw17","weeksTillElection":3,"freq":66},{"party":"AfD","hashtags":"btw17","weeksTillElection":4,"freq":58},{"party":"AfD","hashtags":"btw17","weeksTillElection":5,"freq":98},{"party":"AfD","hashtags":"btw17","weeksTillElection":6,"freq":42},{"party":"AfD","hashtags":"btw2017","weeksTillElection":0,"freq":106},{"party":"AfD","hashtags":"deutschland","weeksTillElection":-1,"freq":18},{"party":"AfD","hashtags":"freiundkonservativ","weeksTillElection":-3,"freq":19},{"party":"AfD","hashtags":"freiundkonservativ","weeksTillElection":-2,"freq":18},{"party":"AfD","hashtags":"ha","weeksTillElection":-3,"freq":17},{"party":"AfD","hashtags":"ha","weeksTillElection":-2,"freq":35},{"party":"AfD","hashtags":"ha","weeksTillElection":-1,"freq":16},{"party":"AfD","hashtags":"ha","weeksTillElection":4,"freq":34},{"party":"AfD","hashtags":"ha","weeksTillElection":6,"freq":37},{"party":"AfD","hashtags":"ltnrw","weeksTillElection":1,"freq":54},{"party":"AfD","hashtags":"ltwnds","weeksTillElection":-3,"freq":18},{"party":"AfD","hashtags":"merkel","weeksTillElection":2,"freq":66},{"party":"AfD","hashtags":"merkel","weeksTillElection":3,"freq":39},{"party":"AfD","hashtags":"merkel","weeksTillElection":4,"freq":31},{"party":"AfD","hashtags":"merkel","weeksTillElection":5,"freq":35},{"party":"AfD","hashtags":"merkel","weeksTillElection":6,"freq":23},{"party":"AfD","hashtags":"nrw","weeksTillElection":-1,"freq":16},{"party":"AfD","hashtags":"obergrenze","weeksTillElection":-2,"freq":18},{"party":"AfD","hashtags":"spd","weeksTillElection":-2,"freq":20},{"party":"AfD","hashtags":"spd","weeksTillElection":-1,"freq":22},{"party":"AfD","hashtags":"spd","weeksTillElection":0,"freq":108},{"party":"AfD","hashtags":"spd","weeksTillElection":1,"freq":51},{"party":"AfD","hashtags":"spd","weeksTillElection":3,"freq":37},{"party":"AfD","hashtags":"tagderdeutscheneinheit","weeksTillElection":-1,"freq":20},{"party":"AfD","hashtags":"traudichdeutschland","weeksTillElection":0,"freq":371},{"party":"AfD","hashtags":"traudichdeutschland","weeksTillElection":1,"freq":191},{"party":"AfD","hashtags":"traudichdeutschland","weeksTillElection":2,"freq":196},{"party":"AfD","hashtags":"traudichdeutschland","weeksTillElection":3,"freq":97},{"party":"AfD","hashtags":"traudichdeutschland","weeksTillElection":4,"freq":105},{"party":"AfD","hashtags":"traudichdeutschland","weeksTillElection":5,"freq":179},{"party":"AfD","hashtags":"traudichdeutschland","weeksTillElection":6,"freq":89},{"party":"AfD","hashtags":"tvduell","weeksTillElection":2,"freq":99},{"party":"CDU","hashtags":"100hcdu","weeksTillElection":0,"freq":88},{"party":"CDU","hashtags":"brandenburg","weeksTillElection":-2,"freq":30},{"party":"CDU","hashtags":"btw17","weeksTillElection":0,"freq":381},{"party":"CDU","hashtags":"btw17","weeksTillElection":1,"freq":135},{"party":"CDU","hashtags":"btw17","weeksTillElection":2,"freq":141},{"party":"CDU","hashtags":"btw17","weeksTillElection":3,"freq":83},{"party":"CDU","hashtags":"btw17","weeksTillElection":4,"freq":127},{"party":"CDU","hashtags":"btw17","weeksTillElection":5,"freq":79},{"party":"CDU","hashtags":"btw17","weeksTillElection":6,"freq":67},{"party":"CDU","hashtags":"cdu","weeksTillElection":-3,"freq":26},{"party":"CDU","hashtags":"cdu","weeksTillElection":-2,"freq":25},{"party":"CDU","hashtags":"cdu","weeksTillElection":-1,"freq":28},{"party":"CDU","hashtags":"cdu","weeksTillElection":0,"freq":179},{"party":"CDU","hashtags":"cdu","weeksTillElection":1,"freq":108},{"party":"CDU","hashtags":"cdu","weeksTillElection":3,"freq":83},{"party":"CDU","hashtags":"cdu","weeksTillElection":4,"freq":59},{"party":"CDU","hashtags":"cdu","weeksTillElection":5,"freq":40},{"party":"CDU","hashtags":"cdu","weeksTillElection":6,"freq":41},{"party":"CDU","hashtags":"dlt17","weeksTillElection":-2,"freq":29},{"party":"CDU","hashtags":"dlt17","weeksTillElection":-1,"freq":79},{"party":"CDU","hashtags":"fa","weeksTillElection":4,"freq":29},{"party":"CDU","hashtags":"fedidwgugl","weeksTillElection":0,"freq":198},{"party":"CDU","hashtags":"fedidwgugl","weeksTillElection":1,"freq":143},{"party":"CDU","hashtags":"fedidwgugl","weeksTillElection":2,"freq":169},{"party":"CDU","hashtags":"fedidwgugl","weeksTillElection":3,"freq":94},{"party":"CDU","hashtags":"fedidwgugl","weeksTillElection":4,"freq":99},{"party":"CDU","hashtags":"fedidwgugl","weeksTillElection":5,"freq":103},{"party":"CDU","hashtags":"fedidwgugl","weeksTillElection":6,"freq":32},{"party":"CDU","hashtags":"klartext","weeksTillElection":1,"freq":91},{"party":"CDU","hashtags":"kreisreform","weeksTillElection":-2,"freq":28},{"party":"CDU","hashtags":"merkel","weeksTillElection":-1,"freq":41},{"party":"CDU","hashtags":"merkel","weeksTillElection":0,"freq":102},{"party":"CDU","hashtags":"merkel","weeksTillElection":1,"freq":80},{"party":"CDU","hashtags":"merkel","weeksTillElection":2,"freq":184},{"party":"CDU","hashtags":"merkel","weeksTillElection":3,"freq":67},{"party":"CDU","hashtags":"merkel","weeksTillElection":4,"freq":74},{"party":"CDU","hashtags":"merkel","weeksTillElection":5,"freq":45},{"party":"CDU","hashtags":"nrw","weeksTillElection":-3,"freq":16},{"party":"CDU","hashtags":"nrw","weeksTillElection":-1,"freq":23},{"party":"CDU","hashtags":"r2g","weeksTillElection":-3,"freq":16},{"party":"CDU","hashtags":"r2g","weeksTillElection":3,"freq":44},{"party":"CDU","hashtags":"r2g","weeksTillElection":5,"freq":38},{"party":"CDU","hashtags":"r2g","weeksTillElection":6,"freq":21},{"party":"CDU","hashtags":"sachsen","weeksTillElection":-3,"freq":19},{"party":"CDU","hashtags":"schulz","weeksTillElection":2,"freq":111},{"party":"CDU","hashtags":"spd","weeksTillElection":5,"freq":38},{"party":"CDU","hashtags":"spd","weeksTillElection":6,"freq":46},{"party":"CDU","hashtags":"tagderdeutscheneinheit","weeksTillElection":-1,"freq":23},{"party":"CDU","hashtags":"tde2017","weeksTillElection":-1,"freq":46},{"party":"CDU","hashtags":"tillich","weeksTillElection":-3,"freq":23},{"party":"CDU","hashtags":"tvduell","weeksTillElection":2,"freq":517},{"party":"CDU","hashtags":"vibb","weeksTillElection":-2,"freq":34},{"party":"CSU","hashtags":"angelamerkel","weeksTillElection":2,"freq":11},{"party":"CSU","hashtags":"annewill","weeksTillElection":-1,"freq":5},{"party":"CSU","hashtags":"barcelona","weeksTillElection":5,"freq":13},{"party":"CSU","hashtags":"bayern","weeksTillElection":-2,"freq":4},{"party":"CSU","hashtags":"bfklang","weeksTillElection":4,"freq":7},{"party":"CSU","hashtags":"btw17","weeksTillElection":0,"freq":41},{"party":"CSU","hashtags":"btw17","weeksTillElection":1,"freq":7},{"party":"CSU","hashtags":"btw17","weeksTillElection":3,"freq":5},{"party":"CSU","hashtags":"btw17","weeksTillElection":4,"freq":8},{"party":"CSU","hashtags":"btw17","weeksTillElection":5,"freq":5},{"party":"CSU","hashtags":"btw2017","weeksTillElection":0,"freq":11},{"party":"CSU","hashtags":"btw2017","weeksTillElection":1,"freq":5},{"party":"CSU","hashtags":"charlottesville","weeksTillElection":5,"freq":4},{"party":"CSU","hashtags":"china","weeksTillElection":5,"freq":4},{"party":"CSU","hashtags":"csu","weeksTillElection":0,"freq":31},{"party":"CSU","hashtags":"csu","weeksTillElection":1,"freq":10},{"party":"CSU","hashtags":"csu","weeksTillElection":2,"freq":11},{"party":"CSU","hashtags":"csu","weeksTillElection":3,"freq":3},{"party":"CSU","hashtags":"csu","weeksTillElection":5,"freq":4},{"party":"CSU","hashtags":"csu","weeksTillElection":6,"freq":4},{"party":"CSU","hashtags":"dbp17","weeksTillElection":-2,"freq":4},{"party":"CSU","hashtags":"dhdl","weeksTillElection":-3,"freq":5},{"party":"CSU","hashtags":"dhdl","weeksTillElection":-2,"freq":9},{"party":"CSU","hashtags":"dhdl","weeksTillElection":-1,"freq":6},{"party":"CSU","hashtags":"dhdl","weeksTillElection":0,"freq":22},{"party":"CSU","hashtags":"dhdl","weeksTillElection":2,"freq":11},{"party":"CSU","hashtags":"diesel","weeksTillElection":3,"freq":3},{"party":"CSU","hashtags":"dressforsuccess","weeksTillElection":3,"freq":3},{"party":"CSU","hashtags":"erdogan","weeksTillElection":5,"freq":4},{"party":"CSU","hashtags":"familienunternehmen","weeksTillElection":-3,"freq":4},{"party":"CSU","hashtags":"familienunternehmen","weeksTillElection":-2,"freq":7},{"party":"CSU","hashtags":"familienunternehmen","weeksTillElection":-1,"freq":4},{"party":"CSU","hashtags":"fcn","weeksTillElection":-2,"freq":3},{"party":"CSU","hashtags":"fedidwgugl","weeksTillElection":4,"freq":7},{"party":"CSU","hashtags":"g20","weeksTillElection":3,"freq":3},{"party":"CSU","hashtags":"jamaika","weeksTillElection":-3,"freq":5},{"party":"CSU","hashtags":"jamaika","weeksTillElection":-1,"freq":6},{"party":"CSU","hashtags":"katalonien","weeksTillElection":-1,"freq":6},{"party":"CSU","hashtags":"klartext","weeksTillElection":1,"freq":11},{"party":"CSU","hashtags":"ltwnds17","weeksTillElection":-3,"freq":4},{"party":"CSU","hashtags":"maut","weeksTillElection":4,"freq":6},{"party":"CSU","hashtags":"merkel","weeksTillElection":1,"freq":8},{"party":"CSU","hashtags":"merkel","weeksTillElection":3,"freq":7},{"party":"CSU","hashtags":"merkel","weeksTillElection":4,"freq":8},{"party":"CSU","hashtags":"myanmar","weeksTillElection":1,"freq":5},{"party":"CSU","hashtags":"nordkorea","weeksTillElection":0,"freq":11},{"party":"CSU","hashtags":"nordkorea","weeksTillElection":3,"freq":4},{"party":"CSU","hashtags":"nordkorea","weeksTillElection":5,"freq":10},{"party":"CSU","hashtags":"nordkorea","weeksTillElection":6,"freq":20},{"party":"CSU","hashtags":"rohingya","weeksTillElection":1,"freq":5},{"party":"CSU","hashtags":"scha","weeksTillElection":-2,"freq":3},{"party":"CSU","hashtags":"schulz","weeksTillElection":2,"freq":20},{"party":"CSU","hashtags":"sondierungen","weeksTillElection":-3,"freq":4},{"party":"CSU","hashtags":"spd","weeksTillElection":3,"freq":3},{"party":"CSU","hashtags":"spd","weeksTillElection":6,"freq":4},{"party":"CSU","hashtags":"tdot17","weeksTillElection":3,"freq":5},{"party":"CSU","hashtags":"teammerkel","weeksTillElection":2,"freq":12},{"party":"CSU","hashtags":"trump","weeksTillElection":6,"freq":6},{"party":"CSU","hashtags":"tvduell","weeksTillElection":2,"freq":88},{"party":"CSU","hashtags":"usa","weeksTillElection":5,"freq":4},{"party":"CSU","hashtags":"usa","weeksTillElection":6,"freq":6},{"party":"CSU","hashtags":"wirtschaft","weeksTillElection":3,"freq":3},{"party":"DIE LINKE","hashtags":"afd","weeksTillElection":-3,"freq":30},{"party":"DIE LINKE","hashtags":"afd","weeksTillElection":-2,"freq":36},{"party":"DIE LINKE","hashtags":"afd","weeksTillElection":-1,"freq":36},{"party":"DIE LINKE","hashtags":"afd","weeksTillElection":0,"freq":254},{"party":"DIE LINKE","hashtags":"afd","weeksTillElection":1,"freq":114},{"party":"DIE LINKE","hashtags":"afd","weeksTillElection":2,"freq":73},{"party":"DIE LINKE","hashtags":"afd","weeksTillElection":3,"freq":109},{"party":"DIE LINKE","hashtags":"agh","weeksTillElection":-3,"freq":55},{"party":"DIE LINKE","hashtags":"agh","weeksTillElection":1,"freq":109},{"party":"DIE LINKE","hashtags":"berlin","weeksTillElection":-3,"freq":28},{"party":"DIE LINKE","hashtags":"berlin","weeksTillElection":-2,"freq":40},{"party":"DIE LINKE","hashtags":"berlin","weeksTillElection":-1,"freq":23},{"party":"DIE LINKE","hashtags":"berlin","weeksTillElection":2,"freq":62},{"party":"DIE LINKE","hashtags":"berlin","weeksTillElection":5,"freq":41},{"party":"DIE LINKE","hashtags":"berlin","weeksTillElection":6,"freq":31},{"party":"DIE LINKE","hashtags":"btw17","weeksTillElection":0,"freq":613},{"party":"DIE LINKE","hashtags":"btw17","weeksTillElection":1,"freq":236},{"party":"DIE LINKE","hashtags":"btw17","weeksTillElection":2,"freq":185},{"party":"DIE LINKE","hashtags":"btw17","weeksTillElection":3,"freq":124},{"party":"DIE LINKE","hashtags":"btw17","weeksTillElection":4,"freq":90},{"party":"DIE LINKE","hashtags":"btw17","weeksTillElection":5,"freq":86},{"party":"DIE LINKE","hashtags":"btw17","weeksTillElection":6,"freq":76},{"party":"DIE LINKE","hashtags":"catalanreferendum","weeksTillElection":-1,"freq":25},{"party":"DIE LINKE","hashtags":"cdu","weeksTillElection":3,"freq":59},{"party":"DIE LINKE","hashtags":"cdu","weeksTillElection":4,"freq":31},{"party":"DIE LINKE","hashtags":"cdu","weeksTillElection":6,"freq":30},{"party":"DIE LINKE","hashtags":"charlottesville","weeksTillElection":5,"freq":36},{"party":"DIE LINKE","hashtags":"endegelaende","weeksTillElection":4,"freq":60},{"party":"DIE LINKE","hashtags":"g20","weeksTillElection":-1,"freq":27},{"party":"DIE LINKE","hashtags":"g20","weeksTillElection":6,"freq":32},{"party":"DIE LINKE","hashtags":"katalonien","weeksTillElection":-2,"freq":44},{"party":"DIE LINKE","hashtags":"katalonien","weeksTillElection":-1,"freq":39},{"party":"DIE LINKE","hashtags":"lichtenhagen","weeksTillElection":4,"freq":40},{"party":"DIE LINKE","hashtags":"linke","weeksTillElection":-3,"freq":34},{"party":"DIE LINKE","hashtags":"linke","weeksTillElection":0,"freq":191},{"party":"DIE LINKE","hashtags":"linke","weeksTillElection":3,"freq":47},{"party":"DIE LINKE","hashtags":"linke","weeksTillElection":5,"freq":38},{"party":"DIE LINKE","hashtags":"linksunten","weeksTillElection":4,"freq":51},{"party":"DIE LINKE","hashtags":"merkel","weeksTillElection":2,"freq":57},{"party":"DIE LINKE","hashtags":"noafd","weeksTillElection":0,"freq":95},{"party":"DIE LINKE","hashtags":"obergrenze","weeksTillElection":-2,"freq":32},{"party":"DIE LINKE","hashtags":"r2g","weeksTillElection":-3,"freq":44},{"party":"DIE LINKE","hashtags":"r2g","weeksTillElection":-2,"freq":46},{"party":"DIE LINKE","hashtags":"r2g","weeksTillElection":-1,"freq":23},{"party":"DIE LINKE","hashtags":"r2g","weeksTillElection":0,"freq":118},{"party":"DIE LINKE","hashtags":"r2g","weeksTillElection":1,"freq":82},{"party":"DIE LINKE","hashtags":"r2g","weeksTillElection":3,"freq":43},{"party":"DIE LINKE","hashtags":"r2g","weeksTillElection":5,"freq":51},{"party":"DIE LINKE","hashtags":"sachsen","weeksTillElection":-3,"freq":28},{"party":"DIE LINKE","hashtags":"tegelschliessen","weeksTillElection":1,"freq":71},{"party":"DIE LINKE","hashtags":"tegelschliessen","weeksTillElection":6,"freq":27},{"party":"DIE LINKE","hashtags":"tvduell","weeksTillElection":2,"freq":209},{"party":"FDP","hashtags":"agh","weeksTillElection":-3,"freq":13},{"party":"FDP","hashtags":"agh","weeksTillElection":-2,"freq":11},{"party":"FDP","hashtags":"agh","weeksTillElection":1,"freq":73},{"party":"FDP","hashtags":"airberlin","weeksTillElection":5,"freq":6},{"party":"FDP","hashtags":"annewill","weeksTillElection":4,"freq":34},{"party":"FDP","hashtags":"badenwa","weeksTillElection":-2,"freq":12},{"party":"FDP","hashtags":"berlinbrauchttegel","weeksTillElection":1,"freq":21},{"party":"FDP","hashtags":"bpt17","weeksTillElection":0,"freq":84},{"party":"FDP","hashtags":"btw17","weeksTillElection":0,"freq":207},{"party":"FDP","hashtags":"btw17","weeksTillElection":1,"freq":56},{"party":"FDP","hashtags":"btw17","weeksTillElection":2,"freq":65},{"party":"FDP","hashtags":"btw17","weeksTillElection":3,"freq":42},{"party":"FDP","hashtags":"btw17","weeksTillElection":4,"freq":35},{"party":"FDP","hashtags":"btw17","weeksTillElection":5,"freq":15},{"party":"FDP","hashtags":"btw17","weeksTillElection":6,"freq":24},{"party":"FDP","hashtags":"denkenwirneu","weeksTillElection":0,"freq":81},{"party":"FDP","hashtags":"denkenwirneu","weeksTillElection":1,"freq":26},{"party":"FDP","hashtags":"denkenwirneu","weeksTillElection":2,"freq":38},{"party":"FDP","hashtags":"denkenwirneu","weeksTillElection":3,"freq":44},{"party":"FDP","hashtags":"denkenwirneu","weeksTillElection":4,"freq":26},{"party":"FDP","hashtags":"denkenwirneu","weeksTillElection":5,"freq":12},{"party":"FDP","hashtags":"denkenwirneu","weeksTillElection":6,"freq":13},{"party":"FDP","hashtags":"dfbpokal","weeksTillElection":6,"freq":10},{"party":"FDP","hashtags":"fa","weeksTillElection":2,"freq":48},{"party":"FDP","hashtags":"fdp","weeksTillElection":-3,"freq":19},{"party":"FDP","hashtags":"fdp","weeksTillElection":-2,"freq":23},{"party":"FDP","hashtags":"fdp","weeksTillElection":-1,"freq":16},{"party":"FDP","hashtags":"fdp","weeksTillElection":0,"freq":165},{"party":"FDP","hashtags":"fdp","weeksTillElection":1,"freq":56},{"party":"FDP","hashtags":"fdp","weeksTillElection":2,"freq":41},{"party":"FDP","hashtags":"fdp","weeksTillElection":3,"freq":55},{"party":"FDP","hashtags":"fdp","weeksTillElection":4,"freq":45},{"party":"FDP","hashtags":"fdp","weeksTillElection":5,"freq":19},{"party":"FDP","hashtags":"fdp","weeksTillElection":6,"freq":18},{"party":"FDP","hashtags":"ltskoe","weeksTillElection":6,"freq":10},{"party":"FDP","hashtags":"ltwnds","weeksTillElection":-3,"freq":10},{"party":"FDP","hashtags":"ltwnds","weeksTillElection":5,"freq":6},{"party":"FDP","hashtags":"ltwnds17","weeksTillElection":-3,"freq":9},{"party":"FDP","hashtags":"netzdg","weeksTillElection":-1,"freq":9},{"party":"FDP","hashtags":"niedersachsen","weeksTillElection":-3,"freq":8},{"party":"FDP","hashtags":"nrw","weeksTillElection":-1,"freq":12},{"party":"FDP","hashtags":"nrw","weeksTillElection":3,"freq":17},{"party":"FDP","hashtags":"nrwkoalition","weeksTillElection":-1,"freq":12},{"party":"FDP","hashtags":"pforzheim","weeksTillElection":-2,"freq":11},{"party":"FDP","hashtags":"pforzheim","weeksTillElection":-1,"freq":9},{"party":"FDP","hashtags":"tegel","weeksTillElection":0,"freq":61},{"party":"FDP","hashtags":"thermilindner","weeksTillElection":4,"freq":22},{"party":"FDP","hashtags":"trendwende","weeksTillElection":-2,"freq":11},{"party":"FDP","hashtags":"tvduell","weeksTillElection":2,"freq":68},{"party":"FDP","hashtags":"wahl2017","weeksTillElection":3,"freq":30},{"party":"GRUENE","hashtags":"afd","weeksTillElection":-2,"freq":27},{"party":"GRUENE","hashtags":"afd","weeksTillElection":-1,"freq":42},{"party":"GRUENE","hashtags":"afd","weeksTillElection":0,"freq":265},{"party":"GRUENE","hashtags":"afd","weeksTillElection":1,"freq":89},{"party":"GRUENE","hashtags":"afd","weeksTillElection":2,"freq":103},{"party":"GRUENE","hashtags":"afd","weeksTillElection":3,"freq":93},{"party":"GRUENE","hashtags":"afd","weeksTillElection":5,"freq":32},{"party":"GRUENE","hashtags":"agh","weeksTillElection":-3,"freq":43},{"party":"GRUENE","hashtags":"barcelona","weeksTillElection":5,"freq":32},{"party":"GRUENE","hashtags":"btw17","weeksTillElection":0,"freq":976},{"party":"GRUENE","hashtags":"btw17","weeksTillElection":1,"freq":249},{"party":"GRUENE","hashtags":"btw17","weeksTillElection":2,"freq":266},{"party":"GRUENE","hashtags":"btw17","weeksTillElection":3,"freq":142},{"party":"GRUENE","hashtags":"btw17","weeksTillElection":4,"freq":119},{"party":"GRUENE","hashtags":"btw17","weeksTillElection":5,"freq":77},{"party":"GRUENE","hashtags":"btw17","weeksTillElection":6,"freq":76},{"party":"GRUENE","hashtags":"darumgra","weeksTillElection":0,"freq":185},{"party":"GRUENE","hashtags":"darumgra","weeksTillElection":1,"freq":102},{"party":"GRUENE","hashtags":"darumgra","weeksTillElection":3,"freq":56},{"party":"GRUENE","hashtags":"darumgra","weeksTillElection":4,"freq":50},{"party":"GRUENE","hashtags":"darumgra","weeksTillElection":5,"freq":44},{"party":"GRUENE","hashtags":"darumgruen","weeksTillElection":0,"freq":527},{"party":"GRUENE","hashtags":"darumgruen","weeksTillElection":1,"freq":204},{"party":"GRUENE","hashtags":"darumgruen","weeksTillElection":2,"freq":210},{"party":"GRUENE","hashtags":"darumgruen","weeksTillElection":3,"freq":119},{"party":"GRUENE","hashtags":"darumgruen","weeksTillElection":4,"freq":93},{"party":"GRUENE","hashtags":"darumgruen","weeksTillElection":5,"freq":58},{"party":"GRUENE","hashtags":"darumgruen","weeksTillElection":6,"freq":62},{"party":"GRUENE","hashtags":"ehefueralle","weeksTillElection":-1,"freq":37},{"party":"GRUENE","hashtags":"endegelaende","weeksTillElection":4,"freq":68},{"party":"GRUENE","hashtags":"gra","weeksTillElection":-3,"freq":48},{"party":"GRUENE","hashtags":"gra","weeksTillElection":-2,"freq":66},{"party":"GRUENE","hashtags":"gra","weeksTillElection":-1,"freq":89},{"party":"GRUENE","hashtags":"gra","weeksTillElection":0,"freq":311},{"party":"GRUENE","hashtags":"gra","weeksTillElection":1,"freq":129},{"party":"GRUENE","hashtags":"gra","weeksTillElection":2,"freq":179},{"party":"GRUENE","hashtags":"gra","weeksTillElection":3,"freq":113},{"party":"GRUENE","hashtags":"gra","weeksTillElection":4,"freq":76},{"party":"GRUENE","hashtags":"gra","weeksTillElection":5,"freq":86},{"party":"GRUENE","hashtags":"gra","weeksTillElection":6,"freq":85},{"party":"GRUENE","hashtags":"heimat","weeksTillElection":-1,"freq":47},{"party":"GRUENE","hashtags":"jamaika","weeksTillElection":-3,"freq":50},{"party":"GRUENE","hashtags":"jamaika","weeksTillElection":-2,"freq":30},{"party":"GRUENE","hashtags":"jetzterstrecht","weeksTillElection":6,"freq":70},{"party":"GRUENE","hashtags":"ldknds","weeksTillElection":6,"freq":97},{"party":"GRUENE","hashtags":"ltwnds","weeksTillElection":-3,"freq":56},{"party":"GRUENE","hashtags":"ltwnds","weeksTillElection":-2,"freq":73},{"party":"GRUENE","hashtags":"ltwnds","weeksTillElection":-1,"freq":68},{"party":"GRUENE","hashtags":"ltwnds17","weeksTillElection":-3,"freq":30},{"party":"GRUENE","hashtags":"obergrenze","weeksTillElection":-2,"freq":39},{"party":"GRUENE","hashtags":"tvduell","weeksTillElection":2,"freq":516},{"party":"SPD","hashtags":"72hspd","weeksTillElection":0,"freq":69},{"party":"SPD","hashtags":"afd","weeksTillElection":3,"freq":46},{"party":"SPD","hashtags":"barcelona","weeksTillElection":5,"freq":50},{"party":"SPD","hashtags":"berlin","weeksTillElection":-1,"freq":24},{"party":"SPD","hashtags":"berlin","weeksTillElection":5,"freq":30},{"party":"SPD","hashtags":"berlin","weeksTillElection":6,"freq":20},{"party":"SPD","hashtags":"btw17","weeksTillElection":0,"freq":366},{"party":"SPD","hashtags":"btw17","weeksTillElection":1,"freq":154},{"party":"SPD","hashtags":"btw17","weeksTillElection":2,"freq":90},{"party":"SPD","hashtags":"btw17","weeksTillElection":3,"freq":82},{"party":"SPD","hashtags":"btw17","weeksTillElection":4,"freq":64},{"party":"SPD","hashtags":"btw17","weeksTillElection":5,"freq":58},{"party":"SPD","hashtags":"btw17","weeksTillElection":6,"freq":47},{"party":"SPD","hashtags":"cdu","weeksTillElection":-2,"freq":25},{"party":"SPD","hashtags":"coecongress","weeksTillElection":-3,"freq":17},{"party":"SPD","hashtags":"esistzeit","weeksTillElection":0,"freq":125},{"party":"SPD","hashtags":"esistzeit","weeksTillElection":1,"freq":73},{"party":"SPD","hashtags":"klartext","weeksTillElection":1,"freq":97},{"party":"SPD","hashtags":"ltwnds","weeksTillElection":-3,"freq":21},{"party":"SPD","hashtags":"ltwnds17","weeksTillElection":-3,"freq":38},{"party":"SPD","hashtags":"ltwnds17","weeksTillElection":-2,"freq":40},{"party":"SPD","hashtags":"martinmachts","weeksTillElection":2,"freq":198},{"party":"SPD","hashtags":"merkel","weeksTillElection":1,"freq":48},{"party":"SPD","hashtags":"merkel","weeksTillElection":2,"freq":83},{"party":"SPD","hashtags":"merkel","weeksTillElection":4,"freq":27},{"party":"SPD","hashtags":"merkel","weeksTillElection":5,"freq":29},{"party":"SPD","hashtags":"merkel","weeksTillElection":6,"freq":21},{"party":"SPD","hashtags":"niedersachsen","weeksTillElection":-3,"freq":23},{"party":"SPD","hashtags":"obergrenze","weeksTillElection":-2,"freq":27},{"party":"SPD","hashtags":"spd","weeksTillElection":-3,"freq":65},{"party":"SPD","hashtags":"spd","weeksTillElection":-2,"freq":59},{"party":"SPD","hashtags":"spd","weeksTillElection":-1,"freq":50},{"party":"SPD","hashtags":"spd","weeksTillElection":0,"freq":332},{"party":"SPD","hashtags":"spd","weeksTillElection":1,"freq":134},{"party":"SPD","hashtags":"spd","weeksTillElection":2,"freq":153},{"party":"SPD","hashtags":"spd","weeksTillElection":3,"freq":106},{"party":"SPD","hashtags":"spd","weeksTillElection":4,"freq":90},{"party":"SPD","hashtags":"spd","weeksTillElection":5,"freq":84},{"party":"SPD","hashtags":"spd","weeksTillElection":6,"freq":59},{"party":"SPD","hashtags":"tagderdeutscheneinheit","weeksTillElection":-1,"freq":22},{"party":"SPD","hashtags":"tde2017","weeksTillElection":-1,"freq":51},{"party":"SPD","hashtags":"tvduell","weeksTillElection":-2,"freq":56},{"party":"SPD","hashtags":"tvduell","weeksTillElection":2,"freq":557},{"party":"SPD","hashtags":"twesten","weeksTillElection":6,"freq":25},{"party":"SPD","hashtags":"wahlarena","weeksTillElection":0,"freq":104},{"party":"SPD","hashtags":"xavier","weeksTillElection":-1,"freq":18},{"party":"SPD","hashtags":"zeitfa","weeksTillElection":3,"freq":55},{"party":"SPD","hashtags":"zeitfa","weeksTillElection":4,"freq":40},{"party":"SPD","hashtags":"zeitfuermartin","weeksTillElection":3,"freq":44},{"party":"SPD","hashtags":"zeitfuermartin","weeksTillElection":4,"freq":26}]
